{
    "id": "OSSA-20250129-5133",
    "version": "1.0.0",
    "severity": "Informational",
    "description": "Haskell array library documentation",
    "title": "Advisory for ghc9.6-array-doc",
    "package_name": "ghc9.6-array-doc",
    "publisher": "Generated by OSSA Collector",
    "last_updated": "2025-01-29T14:54:07.925857",
    "approvals": [
        {
            "consumption": true,
            "externalization": true
        }
    ],
    "purls": [
        "pkg:rpm/almalinux/ghc9.6-array-doc@0.5.6.0"
    ],
    "regex": [
        "^pkg:rpm/almalinux/ghc9.6-array-doc.*"
    ],
    "affected_versions": [
        "*.*",
        "0.5.6.0"
    ],
    "artifacts": [],
    "licenses": "BSD-3-Clause, HaskellReport",
    "aliases": [],
    "references": "https://haskell.org/ghc/"
}