{
    "id": "OSSA-20250129-4128",
    "version": "1.0.0",
    "severity": "Informational",
    "description": "Haskell haddock-library library development files",
    "title": "Advisory for ghc-haddock-library-devel",
    "package_name": "ghc-haddock-library-devel",
    "publisher": "Generated by OSSA Collector",
    "last_updated": "2025-01-29T13:48:15.227691",
    "approvals": [
        {
            "consumption": true,
            "externalization": true
        }
    ],
    "purls": [
        "pkg:rpm/almalinux/ghc-haddock-library-devel@1.10.0"
    ],
    "regex": [
        "^pkg:rpm/almalinux/ghc-haddock-library-devel.*"
    ],
    "affected_versions": [
        "*.*",
        "1.10.0"
    ],
    "artifacts": [
        {
            "url": "file://haddock-library-1.10.0.tar.gz",
            "hashes": {
                "sha1": "a3cd394e050640ed9bb23bd8102515036fa4931d",
                "sha256": "f806c7d5a07d63166101332664c345278f88a5781a640ec3ef215c8fb0015395",
                "ssdeep": "768:lYa/fcyvFyyJaSMYYo1c8QfhVHkkZVIn2mKETrYnnVC:zcytTg7+5QfPHkkZVIHKEgQ",
                "swhid": "swh:1:cnt:a3cd394e050640ed9bb23bd8102515036fa4931d"
            },
            "swhid": "swh:1:dir:4bb174f8bdbf42eed1891b63d8a5a5ca144b989c"
        }
    ],
    "licenses": "BSD",
    "aliases": [],
    "references": "https://hackage.haskell.org/package/haddock-library"
}