{
    "id": "OSSA-20250129-1753",
    "version": "1.0.0",
    "severity": "Informational",
    "description": "Haskell http-conduit library development files",
    "title": "Advisory for ghc-http-conduit-devel",
    "package_name": "ghc-http-conduit-devel",
    "publisher": "Generated by OSSA Collector",
    "last_updated": "2025-01-29T13:53:34.622181",
    "approvals": [
        {
            "consumption": true,
            "externalization": true
        }
    ],
    "purls": [
        "pkg:rpm/almalinux/ghc-http-conduit-devel@2.3.8"
    ],
    "regex": [
        "^pkg:rpm/almalinux/ghc-http-conduit-devel.*"
    ],
    "affected_versions": [
        "*.*",
        "2.3.8"
    ],
    "artifacts": [
        {
            "url": "file://http-conduit-2.3.8.tar.gz",
            "hashes": {
                "sha1": "a7b7bc88f3c1c6e46dcefee8343e4e001580408b",
                "sha256": "cfbef293856fdcce58618726ff911ca28e2ad07c8522b2cd1cfa2cb6e02542ae",
                "ssdeep": "384:ZYM3cakF0+clNfnq+oAnJqp9P8dLNcnnwIMcxte6QHso8o4tE2h8Ip+DsRCvsLgV:CaK0TlNfq+bn9Kxt7xrooE2aImACvy0",
                "swhid": "swh:1:cnt:a7b7bc88f3c1c6e46dcefee8343e4e001580408b"
            },
            "swhid": "swh:1:dir:9727e415de180ad56571ce66c6223703b7106785"
        }
    ],
    "licenses": "BSD",
    "aliases": [],
    "references": "https://hackage.haskell.org/package/http-conduit"
}