{
    "id": "OSSA-20250121-5005",
    "version": "1.0.0",
    "severity": "Informational",
    "description": "C/C++ library to read/write EDF+ and BDF+ files",
    "title": "Advisory for edflib",
    "package_name": "edflib",
    "publisher": "Generated by OSSA Collector",
    "last_updated": "2025-01-21T08:16:52.129390",
    "approvals": [
        {
            "consumption": true,
            "externalization": true
        }
    ],
    "purls": [
        "pkg:rpm/almalinux/edflib@1.21"
    ],
    "regex": [
        "^pkg:rpm/almalinux/edflib.*"
    ],
    "affected_versions": [
        "*.*",
        "1.21"
    ],
    "artifacts": [
        {
            "url": "file://edflib_121.tar.gz",
            "hashes": {
                "sha1": "6e0e26a7b08aae3784c39c3b4f834abc7fa02f03",
                "sha256": "7a8702faa901c370c7ae8e6851cb4feb75579ea1d94a0e9bd5b69ea9585e54ae",
                "ssdeep": "1536:H/Sy0GBBuQXICt/JEHaKhHmrJ/iB2B7aOl:DxYCIHdB8qBI7L",
                "swhid": "swh:1:cnt:6e0e26a7b08aae3784c39c3b4f834abc7fa02f03"
            },
            "swhid": "swh:1:dir:2f2e6e093abcdd22dde6b572bb232617a6f521dc"
        }
    ],
    "licenses": "BSD-3-Clause",
    "aliases": [],
    "references": "https://gitlab.com/Teuniz/EDFlib/"
}