{
    "id": "OSSA-20250121-9122",
    "version": "1.0.0",
    "severity": "High",
    "description": "Documentation for the dionaea honeypot package",
    "title": "Advisory for dionaea-doc",
    "package_name": "dionaea-doc",
    "publisher": "Generated by OSSA Collector",
    "last_updated": "2025-01-21T06:22:24.610882",
    "approvals": [
        {
            "consumption": true,
            "externalization": true
        }
    ],
    "purls": [
        "pkg:rpm/almalinux/dionaea-doc@0.11.0"
    ],
    "regex": [
        "^pkg:rpm/almalinux/dionaea-doc.*"
    ],
    "affected_versions": [
        "*.*",
        "0.11.0"
    ],
    "artifacts": [
        {
            "url": "file://dionaea-0.11.0-4e459f1.tar.gz",
            "hashes": {
                "sha1": "2dff928bca0293f9db228dc2c0a01f4f99424b36",
                "sha256": "3c710ab0da9c69524ea44a2c42eaa106f349c35608a5e72e3e5a303c85d95078",
                "ssdeep": "12288:IzKhhuGRJghdG6StyPUrdFdu3yxPoORSJ:Ienu33G6ShTpBrQJ",
                "swhid": "swh:1:cnt:2dff928bca0293f9db228dc2c0a01f4f99424b36"
            },
            "swhid": "swh:1:dir:80bea7491ce1164e475bb666fd112b81ae35edd3"
        }
    ],
    "licenses": "GPLv2 with exceptions",
    "aliases": [],
    "references": "https://dionaea.readthedocs.io/"
}