{
    "id": "OSSA-20250121-277",
    "version": "1.0.0",
    "severity": "High",
    "description": "Documentation for BIRD Internet Routing Daemon",
    "title": "Advisory for bird-doc",
    "package_name": "bird-doc",
    "publisher": "Generated by OSSA Collector",
    "last_updated": "2025-01-21T03:52:30.166766",
    "approvals": [
        {
            "consumption": true,
            "externalization": true
        }
    ],
    "purls": [
        "pkg:rpm/almalinux/bird-doc@2.16.1"
    ],
    "regex": [
        "^pkg:rpm/almalinux/bird-doc.*"
    ],
    "affected_versions": [
        "*.*",
        "2.16.1"
    ],
    "artifacts": [
        {
            "url": "file://bird-2.16.1.tar.gz",
            "hashes": {
                "sha1": "f02e42888b71de67f29e7a9631f2b99d9a886a3b",
                "sha256": "f6e59cbccaca62668aea02068724bd427b9ec449c7e0f0fc5681503988c735b4",
                "ssdeep": "24576:xzhR6V72TaN9/1EsxLBRQPESxCL6ZDWr4PsxDig0agSSEj2ri9NgUEHcTAy8Fxmn:ZU72s9ttxL0PESftYSEqmMDHcOU",
                "swhid": "swh:1:cnt:f02e42888b71de67f29e7a9631f2b99d9a886a3b"
            },
            "swhid": "swh:1:dir:2bd8dec3e444b194f44276d7ea3b7da1950f86fd"
        }
    ],
    "licenses": "GPL-2.0-or-later",
    "aliases": [],
    "references": "https://bird.network.cz/"
}