{
    "id": "OSSA-20250129-497",
    "version": "1.0.0",
    "severity": "High",
    "description": "Writes audio CD-Rs in disk-at-once (DAO) mode",
    "title": "Advisory for cdrdao",
    "package_name": "cdrdao",
    "publisher": "Generated by OSSA Collector",
    "last_updated": "2025-01-29T13:21:21.183818",
    "approvals": [
        {
            "consumption": true,
            "externalization": true
        }
    ],
    "purls": [
        "pkg:rpm/almalinux/cdrdao@1.2.4"
    ],
    "regex": [
        "^pkg:rpm/almalinux/cdrdao.*"
    ],
    "affected_versions": [
        "*.*",
        "1.2.4"
    ],
    "artifacts": [
        {
            "url": "file://cdrdao-1.2.4.tar.bz2",
            "hashes": {
                "sha1": "3adfbdefc73728a75c9ddc41160c9fe4139fb1e0",
                "sha256": "358d9cb83370ceaecdc60564cbf14c2ea2636eac60a966e2461c011ba09853b4",
                "ssdeep": "24576:MMZ9NHDDKgF7lxKoWCySNFIwCL35i8SiMeOyk0DQuAYZKGp/G6k4505Qv:MMtD7F7lx+C7VCA9C/VtG6kCiw",
                "swhid": "swh:1:cnt:3adfbdefc73728a75c9ddc41160c9fe4139fb1e0"
            },
            "swhid": "swh:1:dir:1f01630d5a6752738222669997a17002690fabc2"
        }
    ],
    "licenses": "GPLv2+",
    "aliases": [],
    "references": "http://cdrdao.sourceforge.net/"
}