{
    "id": "OSSA-20250121-3459",
    "version": "1.0.0",
    "severity": "Medium",
    "description": "Python bindings for the Compiz Configuration System",
    "title": "Advisory for compizconfig-python",
    "package_name": "compizconfig-python",
    "publisher": "Generated by OSSA Collector",
    "last_updated": "2025-01-21T06:04:52.632681",
    "approvals": [
        {
            "consumption": true,
            "externalization": true
        }
    ],
    "purls": [
        "pkg:rpm/almalinux/compizconfig-python@0.8.18"
    ],
    "regex": [
        "^pkg:rpm/almalinux/compizconfig-python.*"
    ],
    "affected_versions": [
        "*.*",
        "0.8.18"
    ],
    "artifacts": [
        {
            "url": "file://compizconfig-python-v0.8.18.tar.bz2",
            "hashes": {
                "sha1": "14076cc12e4a4ded26472d9f75e28fce45b0ef78",
                "sha256": "2add2083365eee2f966db826c3967f030d949b2b5aad59e738ba3b782587ad93",
                "ssdeep": "384:7LMX2jitiZ4a/gr+1V6+UOJz+YuLEs2OH/8gJj0GsrIdgJrGRZj:7Ljiiu+6+bk9BkSIEqGP",
                "swhid": "swh:1:cnt:14076cc12e4a4ded26472d9f75e28fce45b0ef78"
            },
            "swhid": "swh:1:dir:3173464213138bd55e43e83f7979efde72c0b59b"
        }
    ],
    "licenses": "LGPLv2+",
    "aliases": [],
    "references": "https://gitlab.com/compiz/compizconfig-python"
}