{
    "id": "OSSA-20250121-3710",
    "version": "1.0.0",
    "severity": "Informational",
    "description": "Fd is a simple, fast and user-friendly alternative to find",
    "title": "Advisory for fd-find",
    "package_name": "fd-find",
    "publisher": "Generated by OSSA Collector",
    "last_updated": "2025-01-21T08:47:04.714155",
    "approvals": [
        {
            "consumption": true,
            "externalization": true
        }
    ],
    "purls": [
        "pkg:rpm/almalinux/fd-find@10.1.0"
    ],
    "regex": [
        "^pkg:rpm/almalinux/fd-find.*"
    ],
    "affected_versions": [
        "*.*",
        "10.1.0"
    ],
    "artifacts": [],
    "licenses": "Apache-2.0, Apache-2.0 WITH LLVM-exception, MIT, Unicode-DFS-2016, Unlicense",
    "aliases": [],
    "references": "https://crates.io/crates/fd-find"
}