{
    "id": "OSSA-20250121-977",
    "version": "1.0.0",
    "severity": "High",
    "description": "Calendar applications for Asterisk",
    "title": "Advisory for asterisk-calendar",
    "package_name": "asterisk-calendar",
    "publisher": "Generated by OSSA Collector",
    "last_updated": "2025-01-21T02:47:37.667789",
    "approvals": [
        {
            "consumption": true,
            "externalization": true
        }
    ],
    "purls": [
        "pkg:rpm/almalinux/asterisk-calendar@18.12.1"
    ],
    "regex": [
        "^pkg:rpm/almalinux/asterisk-calendar.*"
    ],
    "affected_versions": [
        "*.*",
        "18.12.1"
    ],
    "artifacts": [
        {
            "url": "file://ansible-collection-community-rabbitmq-1.2.3.tar.gz",
            "hashes": {
                "sha1": "db1febd7a2de2e14d24526023d4c66e7ff25c85f",
                "sha256": "708adfdcae903e6927be7304554ad2d8e262dc441d8bc0514f6664cb61d1bd33",
                "ssdeep": "1536:Ol9SUk4RysQaohUIFGU2sTUazb6qQGWyOYvCZy54W8ghsUAFJM:Ol9S5jdVpb96u5o7FE",
                "swhid": "swh:1:cnt:db1febd7a2de2e14d24526023d4c66e7ff25c85f"
            },
            "swhid": "swh:1:dir:b8ceab39f2872ae1f9b0812cb14580727a8c8c7a"
        }
    ],
    "licenses": "GPLv2",
    "aliases": [],
    "references": "http://www.asterisk.org/"
}