{
    "id": "OSSA-20250121-370",
    "version": "1.0.0",
    "severity": "High",
    "description": "Color terminal highlighter for diff files",
    "title": "Advisory for colordiff",
    "package_name": "colordiff",
    "publisher": "Generated by OSSA Collector",
    "last_updated": "2025-01-21T06:00:16.791600",
    "approvals": [
        {
            "consumption": true,
            "externalization": true
        }
    ],
    "purls": [
        "pkg:rpm/almalinux/colordiff@1.0.21"
    ],
    "regex": [
        "^pkg:rpm/almalinux/colordiff.*"
    ],
    "affected_versions": [
        "*.*",
        "1.0.21"
    ],
    "artifacts": [
        {
            "url": "file://colordiff-1.0.21.tar.gz",
            "hashes": {
                "sha1": "7695033f6ded458b73e8535ea932faafc1622849",
                "sha256": "9b30f4257ef0f0806dea5a27c9ad8edc3f7999f05ddaff6f0627064dc927e615",
                "ssdeep": "384:761jty+6ZBCCp5zsYBYIStWcytB7HEe3iTA8aXaazg6kYExYVrwMPsyeKIXcj0NE:7ZNs1LINBTENANaPe9wzX6SE",
                "swhid": "swh:1:cnt:7695033f6ded458b73e8535ea932faafc1622849"
            },
            "swhid": "swh:1:dir:419d5ef758f27de034e0245ceb915e10d9f2638e"
        }
    ],
    "licenses": "GPLv2+",
    "aliases": [],
    "references": "http://www.colordiff.org/"
}