{
    "id": "OSSA-20250129-5476",
    "version": "1.0.0",
    "severity": "High",
    "description": "AlmaLinux package repositories",
    "title": "Advisory for almalinux-repos",
    "package_name": "almalinux-repos",
    "publisher": "Generated by OSSA Collector",
    "last_updated": "2025-01-29T09:41:18.257088",
    "approvals": [
        {
            "consumption": true,
            "externalization": true
        }
    ],
    "purls": [
        "pkg:rpm/almalinux/almalinux-repos@9.5"
    ],
    "regex": [
        "^pkg:rpm/almalinux/almalinux-repos.*"
    ],
    "affected_versions": [
        "*.*",
        "9.5"
    ],
    "artifacts": [
        {
            "url": "file://SDL_net-1.2.8.tar.gz",
            "hashes": {
                "sha1": "fd393059fef8d9925dc20662baa3b25e02b8405d",
                "sha256": "5f4a7a8bb884f793c278ac3f3713be41980c5eedccecff0260411347714facb4",
                "ssdeep": "6144:yWR3XRUHn8bBSR2jfg15LYSmSGRTliqnT8j3/MwneY17SVT:r3XRUHn8gUj47WRRhVnTySY1GVT",
                "swhid": "swh:1:cnt:fd393059fef8d9925dc20662baa3b25e02b8405d"
            },
            "swhid": "swh:1:dir:12ee13cc7fdbba7ce48e9af73a0c0bc59c4eadf6"
        }
    ],
    "licenses": "GPLv2",
    "aliases": [],
    "references": "https://almalinux.org"
}