{
    "id": "OSSA-20250121-3215",
    "version": "1.0.0",
    "severity": "Informational",
    "description": "Header-only C++ binding for libzmq",
    "title": "Advisory for cppzmq-devel",
    "package_name": "cppzmq-devel",
    "publisher": "Generated by OSSA Collector",
    "last_updated": "2025-01-21T06:09:34.102111",
    "approvals": [
        {
            "consumption": true,
            "externalization": true
        }
    ],
    "purls": [
        "pkg:rpm/almalinux/cppzmq-devel@4.8.1"
    ],
    "regex": [
        "^pkg:rpm/almalinux/cppzmq-devel.*"
    ],
    "affected_versions": [
        "*.*",
        "4.8.1"
    ],
    "artifacts": [
        {
            "url": "file://cppzmq-4.8.1.tar.gz",
            "hashes": {
                "sha1": "056ec2258f099ee8899b93acddc9650d3d86ce7c",
                "sha256": "7a23639a45f3a0049e11a188e29aaedd10b2f4845f0000cf3e22d6774ebde0af",
                "ssdeep": "768:AI2GukmoOtC4XuyQw0JHYGHQD52YVIScjdZqj+vYMibYp5pNEhd4gm:AwukmouWyjEHbwD5lIjhZmwYLOrEhd49",
                "swhid": "swh:1:cnt:056ec2258f099ee8899b93acddc9650d3d86ce7c"
            },
            "swhid": "swh:1:dir:a3836a1e0e344958d70b01e83437744baa55fbaa"
        }
    ],
    "licenses": "MIT",
    "aliases": [],
    "references": "https://zeromq.org"
}