{
    "id": "OSSA-20250121-1792",
    "version": "1.0.0",
    "severity": "Informational",
    "description": "Header-only C++ library for efficient mathematical optimization",
    "title": "Advisory for ensmallen-devel",
    "package_name": "ensmallen-devel",
    "publisher": "Generated by OSSA Collector",
    "last_updated": "2025-01-21T08:27:35.228809",
    "approvals": [
        {
            "consumption": true,
            "externalization": true
        }
    ],
    "purls": [
        "pkg:rpm/almalinux/ensmallen-devel@2.22.1"
    ],
    "regex": [
        "^pkg:rpm/almalinux/ensmallen-devel.*"
    ],
    "affected_versions": [
        "*.*",
        "2.22.1"
    ],
    "artifacts": [
        {
            "url": "file://ensmallen-2.22.1.tar.gz",
            "hashes": {
                "sha1": "f143cb24bf01f77bd26f63adbfae58bbfb876d2c",
                "sha256": "daf53fe96783043ca33151a3851d054a826fab8d9a173e6bcbbedd4a7eabf5b1",
                "ssdeep": "24576:KjasNzAFohEo+cHqiLGBGW3cFMm5CSt/X46DpK9i5nTbwfQQYj1OrqceAdgHWJvF:KjTzAFohEps1LbFMmn/X46kCnPfj1TQF",
                "swhid": "swh:1:cnt:f143cb24bf01f77bd26f63adbfae58bbfb876d2c"
            },
            "swhid": "swh:1:dir:c4bb701333963004c2a511a49662fd0ce015e09c"
        }
    ],
    "licenses": "BSD-3-Clause",
    "aliases": [],
    "references": "https://www.ensmallen.org"
}