{
    "id": "OSSA-20250121-6483",
    "version": "1.0.0",
    "severity": "Informational",
    "description": "Downloads Certificate Revocation Lists",
    "title": "Advisory for fetch-crl",
    "package_name": "fetch-crl",
    "publisher": "Generated by OSSA Collector",
    "last_updated": "2025-01-21T08:55:22.958847",
    "approvals": [
        {
            "consumption": true,
            "externalization": true
        }
    ],
    "purls": [
        "pkg:rpm/almalinux/fetch-crl@3.0.22"
    ],
    "regex": [
        "^pkg:rpm/almalinux/fetch-crl.*"
    ],
    "affected_versions": [
        "*.*",
        "3.0.22"
    ],
    "artifacts": [
        {
            "url": "file://fetch-crl-3.0.22.tar.gz",
            "hashes": {
                "sha1": "a3e7be780c55b77f8260d20d0c9a5d8c96068ec8",
                "sha256": "09bcf5d1004ac8c3ced5e71b70e6b6afb7f713630aca0afbfa2db3244567cb2b",
                "ssdeep": "768:zIV8htwsP7gphoz41OEhC2GX/s+2TGOyZ6ZDSJGtmSGNfLkShUeKADNyceil:zI6htwchg3GXU+2T2yeGtmhDwADkU",
                "swhid": "swh:1:cnt:a3e7be780c55b77f8260d20d0c9a5d8c96068ec8"
            },
            "swhid": "swh:1:dir:0a0e0f8b1634b58f02c92242be0a8291955e327d"
        }
    ],
    "licenses": "ASL 2.0",
    "aliases": [],
    "references": "https://wiki.nikhef.nl/grid/FetchCRL3"
}